Workbook
Name aporte: Simulador!$D$17
Name patrimonio: Simulador!$D$20
Name perfil_selecionado: Simulador!$D$32
Name qtd_anos: Simulador!$D$18
Name redimento_carteira: Simulador!$D$13
Name rendimento_carteira: Simulador!$D$13
Name salario_bruto: Simulador!$D$12
Name sugestao_investimento: Simulador!$D$14
Name taxa_mensal: Simulador!$D$19

Sheet Simulador
B8: SIMULADOR DE INVESTIMENTO EM FIIs | RIZE NEXUS
B9: Planejamento Financeiro, Projeção de Dividendos e Gestão de Carteira
B11: 1. CONFIGURAÇÕES DE RENDA & CARTEIRA
B12: Salário Bruto Mensal | D12: 2000
B13: Rendimento Estimado da Carteira (a.m.) | D13: 0.006
B14: Sugestão de Investimento (30% do Salário) | D14: =D12*30% -> 600
B16: 2. SIMULAÇÃO DE APORTE & DIVIDENDOS
B17: Quanto investir por mês? | D17: 150
B18: Por quantos anos? | D18: 5
B19: Taxa de Rendimento mensal? | D19: 0.01079
B20: Patrimônio Acumulado Estimado | D20: =FV(taxa_mensal,qtd_anos*12,aporte*-1) -> 12566.537
B21: Dividendos Mensais Estimados | D21: =patrimonio*rendimento_carteira -> 75.399223
B23: 3. PROJEÇÃO DE CENÁRIOS (LONGO PRAZO)
B24: Prazo (Anos) | C24: Patrimônio Acumulado | D24: Dividendos Mensais
A25: 2 | B25: 2 Anos | C25: =FV(taxa_mensal, A25*12, aporte*-1) -> 4084.1441 | D25: =C25*rendimento_carteira -> 24.504865
A26: 5 | B26: 5 Anos | C26: =FV(taxa_mensal, A26*12, aporte*-1) -> 12566.537 | D26: =C26*rendimento_carteira -> 75.399223
A27: 10 | B27: 10 Anos | C27: =FV(taxa_mensal, A27*12, aporte*-1) -> 36492.632 | D27: =C27*rendimento_carteira -> 218.95579
A28: 20 | B28: 20 Anos | C28: =FV(taxa_mensal, A28*12, aporte*-1) -> 168779.76 | D28: =C28*rendimento_carteira -> 1012.6786
A29: 30 | B29: 30 Anos | C29: =FV(taxa_mensal, A29*12, aporte*-1) -> 648325.45 | D29: =C29*rendimento_carteira -> 3889.9527
B31: 4. DIVISÃO DO APORTE POR PERFIL DE INVESTIDOR
B32: Perfil de Investidor Selecionado | D32: Conservador
B33: Valor Total Aportado por Mês | D33: =aporte -> 150
B35: Tipo de FII | C35: Percentual Sugerido | D35: Valor Alocado (R$)
B36: PAPEL | C36: =VLOOKUP(perfil_selecionado&"-"&B36, Apoio!$A:$D, 4, FALSE) -> 0.3 | D36: =C36*$D$33 -> 45
B37: TIJOLO | C37: =VLOOKUP(perfil_selecionado&"-"&B37, Apoio!$A:$D, 4, FALSE) -> 0.5 | D37: =C37*$D$33 -> 75
B38: HÍBRIDOS | C38: =VLOOKUP(perfil_selecionado&"-"&B38, Apoio!$A:$D, 4, FALSE) -> 0.1 | D38: =C38*$D$33 -> 15
B39: FOFS | C39: =VLOOKUP(perfil_selecionado&"-"&B39, Apoio!$A:$D, 4, FALSE) -> 0.1 | D39: =C39*$D$33 -> 15
B40: DESENVOLVIMENTO | C40: =VLOOKUP(perfil_selecionado&"-"&B40, Apoio!$A:$D, 4, FALSE) -> 0 | D40: =C40*$D$33 -> 0
B41: HOTELARIAS | C41: =VLOOKUP(perfil_selecionado&"-"&B41, Apoio!$A:$D, 4, FALSE) -> 0 | D41: =C41*$D$33 -> 0
B42: TOTAL | C42: =SUM(C36:C41) -> 1 | D42: =SUM(D36:D41) -> 150

Sheet Apoio
A1: CHAVE | B1: PERFIL | C1: TIPO DE FII | D1: %
A2: =B2&"-"&C2 -> Conservador-PAPEL | B2: Conservador | C2: PAPEL | D2: 0.3
A3: =B3&"-"&C3 -> Conservador-TIJOLO | B3: Conservador | C3: TIJOLO | D3: 0.5
A4: =B4&"-"&C4 -> Conservador-HÍBRIDOS | B4: Conservador | C4: HÍBRIDOS | D4: 0.1
A5: =B5&"-"&C5 -> Conservador-FOFS | B5: Conservador | C5: FOFS | D5: 0.1
A6: =B6&"-"&C6 -> Conservador-DESENVOLVIMENTO | B6: Conservador | C6: DESENVOLVIMENTO | D6: 0
A7: =B7&"-"&C7 -> Conservador-HOTELARIAS | B7: Conservador | C7: HOTELARIAS | D7: 0
A8: =B8&"-"&C8 -> Moderado-PAPEL | B8: Moderado | C8: PAPEL | D8: 0.32
A9: =B9&"-"&C9 -> Moderado-TIJOLO | B9: Moderado | C9: TIJOLO | D9: 0.35
A10: =B10&"-"&C10 -> Moderado-HÍBRIDOS | B10: Moderado | C10: HÍBRIDOS | D10: 0.08
A11: =B11&"-"&C11 -> Moderado-FOFS | B11: Moderado | C11: FOFS | D11: 0.05
A12: =B12&"-"&C12 -> Moderado-DESENVOLVIMENTO | B12: Moderado | C12: DESENVOLVIMENTO | D12: 0.1
A13: =B13&"-"&C13 -> Moderado-HOTELARIAS | B13: Moderado | C13: HOTELARIAS | D13: 0.1
... A19: =B19&"-"&C19 -> Agressivo-HOTELARIAS | B19: Agressivo | C19: HOTELARIAS | D19: 0.1
